LICENSE.txt
MANIFEST.in
README.md
setup.py
xkcdpassword/__init__.py
xkcdpassword/easywords.txt
xkcdpassword/words.txt
xkcdpassword/xkcdpassword.py
xkcdpassword.egg-info/PKG-INFO
xkcdpassword.egg-info/SOURCES.txt
xkcdpassword.egg-info/dependency_links.txt
xkcdpassword.egg-info/entry_points.txt
xkcdpassword.egg-info/not-zip-safe
xkcdpassword.egg-info/requires.txt
xkcdpassword.egg-info/top_level.txt