Metadata-Version: 1.1
Name: xkcdpassword
Version: 0.6.6
Summary: A generator of xkcd-style passwords
Home-page: https://github.com/dougwritescode/xkcdpassword
Author: Doug Walter
Author-email: dougwritescode@gmail.com
License: MIT
Download-URL: https://github.com/dougwritescode/xkcdpassword/tarball/0.6.6
Keywords: python xkcd utilities security password
Platform: UNKNOWN
Classifier: Development Status :: 3 - Alpha
Classifier: Environment :: Console
Classifier: License :: OSI Approved :: MIT License
Classifier: Natural Language :: English
Classifier: Programming Language :: Python :: 2.7
Classifier: Topic :: Security
Classifier: Topic :: Utilities
